{"otps":[{"to":"359876966554","message-id":"0C00000052A49D5F","status":"0","remaining-balance":"1.28500000","message-price":"0.06500000","network":"28403","otp":"872145"},{"to":"359876966554","message-id":"0B000000734E73BE","status":"0","remaining-balance":"1.22000000","message-price":"0.06500000","network":"28403","otp":"621967"},{"to":"359876966554","message-id":"0C00000052AD992B","status":"0","remaining-balance":"1.15500000","message-price":"0.06500000","network":"28403","otp":"849285"},{"to":"359876966554","message-id":"0C00000052ADA26E","status":"0","remaining-balance":"1.09000000","message-price":"0.06500000","network":"28403","otp":"418962"}]}